typing_unknown/__init__.py
typing_unknown/unknown.py
typing_unknown-0.1.2.dist-info/METADATA
typing_unknown-0.1.2.dist-info/WHEEL
typing_unknown-0.1.2.dist-info/licenses/LICENSE
typing_unknown-0.1.2.dist-info/RECORD
