Metadata-Version: 2.4
Name: typing-unknown
Version: 0.1.2
Summary: Defines Unknown type for Python
Author-email: Ryan Young <dev@ryayoung.com>
License-Expression: MIT
License-File: LICENSE
Classifier: Development Status :: 3 - Alpha
Classifier: Intended Audience :: Developers
Classifier: License :: OSI Approved :: MIT License
Classifier: Operating System :: OS Independent
Classifier: Programming Language :: Python :: 3.12
Classifier: Topic :: Software Development :: Libraries
Requires-Python: >=3.12
